[
  {
    "content_id": 499052,
    "reference_id": 202743,
    "title": "Philemon",
    "media_type": "Text",
    "index_reference": "57000000",
    "language": "eng",
    "content": "<p><strong>What is the book of</strong> <strong>Philemon?</strong></p><ul><li><p>The book of Philemon is a letter from Paul. Timothy helped Paul write it.</p></li><li><p>It’s thought that Paul wrote it around the year AD 60.</p></li></ul><p><strong>Who was Philemon written to?</strong></p><ul><li><p>To Philemon, his family and the church that met in their home.</p></li><li><p>Followers of Jesus recognise that Philemon shares the truth about Jesus. It’s for all people everywhere.</p></li></ul><p><strong>Why was Philemon written?</strong></p><ul><li><p>To ask Philemon to take Onesimus back as a brother and not a slave.</p></li></ul><p><strong>Main ideas</strong></p><ul><li><p>God brought Onesimus and Paul together.</p></li><li><p>The good news changed Onesimus’ life.</p></li><li><p>The good news can change the relationship between a slave owner and a slave.</p></li></ul><p><strong>Outline</strong></p><p><strong>Greetings (1:1–3).</strong></p><p><strong>Prayer and giving thanks (1:4–7).</strong></p><p><strong>Paul makes an appeal for Onesimus (1:8–22).</strong></p><p><strong>Final greetings (1:23–25).</strong></p>",
    "associations": {
      "passage": [
        {
          "start_ref": "57001001",
          "start_ref_usfm": "PHM 1:1",
          "end_ref": "57001001",
          "end_ref_usfm": "PHM 1:1"
        }
      ],
      "resource": []
    }
  }
]